gcon/__main__.py
gcon/__version__.py
gcon/settings.py
gcon/adapters/__init__.py
gcon/adapters/pickledb/__init__.py
gcon/adapters/pickledb/repositories/__init__.py
gcon/adapters/pickledb/repositories/connector.py
gcon/adapters/pickledb/repositories/node_fetching.py
gcon/adapters/pickledb/repositories/node_registration.py
gcon/core/__init__.py
gcon/core/domain/__init__.py
gcon/core/domain/dtos/__init__.py
gcon/core/domain/dtos/connection.py
gcon/core/domain/dtos/metadata.py
gcon/core/domain/dtos/node.py
gcon/core/domain/dtos/score.py
gcon/core/domain/dtos/reference_data/__init__.py
gcon/core/domain/dtos/reference_data/schemas.py
gcon/core/domain/dtos/tests/__init__.py
gcon/core/domain/dtos/tests/test_metadata.py
gcon/core/domain/dtos/tests/test_reference_data.py
gcon/core/domain/dtos/tests/test_schemas.py
gcon/core/domain/entities/__init__.py
gcon/core/domain/entities/node_fetching.py
gcon/core/domain/entities/node_registration.py
gcon/core/use_cases/README.md
gcon/core/use_cases/__init__.py
gcon/core/use_cases/build_metadata_match_scores/__init__.py
gcon/core/use_cases/build_metadata_match_scores/_calculate_connection_match_score.py
gcon/core/use_cases/build_metadata_match_scores/_calculate_connection_observed_score.py
gcon/core/use_cases/collect_metadata/__init__.py
gcon/core/use_cases/collect_metadata/_chunks_accessions.py
gcon/core/use_cases/collect_metadata/_collect_single_gene_metadata.py
gcon/core/use_cases/collect_metadata/_collect_unique_identifiers.py
gcon/core/use_cases/collect_metadata/_place_qualifiers.py
gcon/core/use_cases/load_and_validate_source_table/__init__.py
gcon/core/use_cases/load_and_validate_source_table/_dtos.py
gcon/core/use_cases/load_and_validate_source_table/_validate_genes_fields.py
gcon/core/use_cases/load_and_validate_source_table/_validate_optional_fields.py
gcon/core/use_cases/load_and_validate_source_table/_validate_required_fields.py
gcon/core/use_cases/persist_metadata_on_gc_server/__init__.py
gene_connector_cli-0.6.5.dist-info/LICENSE
gene_connector_cli-0.6.5.dist-info/METADATA
gene_connector_cli-0.6.5.dist-info/WHEEL
gene_connector_cli-0.6.5.dist-info/entry_points.txt
gene_connector_cli-0.6.5.dist-info/top_level.txt
gene_connector_cli-0.6.5.dist-info/RECORD
